pymini/__init__.py
pymini/cli.py
pymini/pymini.py
pymini/utils.py
pymini-0.1.1.dist-info/LICENSE
pymini-0.1.1.dist-info/METADATA
pymini-0.1.1.dist-info/WHEEL
pymini-0.1.1.dist-info/entry_points.txt
pymini-0.1.1.dist-info/top_level.txt
pymini-0.1.1.dist-info/RECORD
