Metadata-Version: 2.1
Name: pymini
Version: 0.1.1
Summary: Minify python
Author-email: Alvin Wan <hi@alvinwan.com>
Project-URL: Homepage, https://github.com/alvinwan/pymini
Project-URL: Bug Tracker, https://github.com/alvinwan/pymini/issues
Classifier: Programming Language :: Python :: 3
Classifier: License :: OSI Approved :: MIT License
Classifier: Operating System :: OS Independent
Requires-Python: >=3.7
License-File: LICENSE
